topsis/__init__.py
topsis/topsis.py
topsis_pritish_102303473-1.0.3.dist-info/METADATA
topsis_pritish_102303473-1.0.3.dist-info/WHEEL
topsis_pritish_102303473-1.0.3.dist-info/entry_points.txt
topsis_pritish_102303473-1.0.3.dist-info/top_level.txt
topsis_pritish_102303473-1.0.3.dist-info/RECORD
